hypy/__init__.py
hypy/abc.py
hypy/auction.py
hypy/auctions.py
hypy/bazaar.py
hypy/bazaaritem.py
hypy/exceptions.py
hypy/guild.py
hypy/guildmember.py
hypy/guildrank.py
hypy/hypixel.py
hypy/hypixelfriend.py
hypy/hypixelfriends.py
hypy/hypixelplayer.py
hypy/hypixelresources.py
hypy/hypyobject.py
hypy/models.py
hypy/mojang.py
hypy/player.py
hypy/playercounts.py
hypy/playerstatus.py
hypy/profile.py
hypy/skyblockinventories.py
hypy/skyblockskills.py
hypy/socialmedia.py
hypy/utils.py
hypy/uuid.py
hypy/vars.py
hypy/ext/__init__.py
hypy/ext/collisions/__init__.py
hypy/ext/collisions/collisions.py
hypy/ext/senither/__init__.py
hypy/ext/senither/senither.py
hypy/ext/senither/vars.py
hypy/ext/senither/weightobject.py
hypy/ext/skyhelper/__init__.py
hypy/ext/skyhelper/skyhelper.py
hypy_hypixel-1.7.0.dist-info/LICENSE
hypy_hypixel-1.7.0.dist-info/METADATA
hypy_hypixel-1.7.0.dist-info/WHEEL
hypy_hypixel-1.7.0.dist-info/top_level.txt
hypy_hypixel-1.7.0.dist-info/RECORD
