Metadata-Version: 2.1
Name: hypy-hypixel
Version: 1.7.0
Summary: A Hypixel API Wrapper
Home-page: https://github.com/PikaFan123/hypy
Author: PikaFan123
License: MIT License
Requires-Python: >=3.8,<4.0
License-File: LICENSE
Requires-Dist: aiohttp
Requires-Dist: dataclasses
Requires-Dist: aiofiles
Requires-Dist: nbt
Requires-Dist: orjson
